sitemap_grabber/__init__.py
sitemap_grabber/sitemap_grabber.py
sitemap_grabber/well_known_files.py
sitemap_grabber-2.0.1.dist-info/LICENSE
sitemap_grabber-2.0.1.dist-info/WHEEL
sitemap_grabber-2.0.1.dist-info/METADATA
sitemap_grabber-2.0.1.dist-info/RECORD
