Metadata-Version: 2.1
Name: sitemap_grabber
Version: 2.0.1
Summary: Grab and recursively parse website sitemaps, robots.txt, and other related files.
Author-email: SimpleCTO <github+sitemap_grabber@simplecto.com>
Requires-Python: >=3.8
Classifier: Development Status :: 4 - Beta
Classifier: Intended Audience :: Developers
Classifier: License :: OSI Approved :: MIT License
Classifier: Programming Language :: Python :: 3
Classifier: Programming Language :: Python :: 3.8
Classifier: Programming Language :: Python :: 3.9
Classifier: Programming Language :: Python :: 3.10
Classifier: Programming Language :: Python :: 3.11
Classifier: Programming Language :: Python :: 3.12
Classifier: Topic :: Internet :: WWW/HTTP :: Indexing/Search
Requires-Dist: defusedxml==0.7.1
Requires-Dist: curl_cffi==0.7.3
Requires-Dist: ruff==0.6.9 ; extra == "dev"
Requires-Dist: pre-commit==4.0.1 ; extra == "dev"
Requires-Dist: flit==3.9.0 ; extra == "dev"
Requires-Dist: mkdocs ; extra == "docs"
Requires-Dist: mkdocs-material ; extra == "docs"
Requires-Dist: mkdocstrings[python] ; extra == "docs"
Project-URL: Documentation, https://github.com/simplecto/sitemap_grabber#readme
Project-URL: Home, https://github.com/simplecto/sitemap_grabber
Project-URL: Issues, https://github.com/simplecto/sitemap_grabber/issues
Project-URL: Source, https://github.com/simplecto/sitemap_grabber
Provides-Extra: dev
Provides-Extra: docs
